ngen_japi/__init__.py
ngen_japi/cli.py
ngen_japi/jenkins.py
ngen_japi-0.1.5.dist-info/METADATA
ngen_japi-0.1.5.dist-info/WHEEL
ngen_japi-0.1.5.dist-info/entry_points.txt
ngen_japi-0.1.5.dist-info/top_level.txt
ngen_japi-0.1.5.dist-info/RECORD
