Metadata-Version: 2.4
Name: ngen-japi
Version: 0.1.5
Summary: Jenkins API management CLI and universal command wrapper package
Author: ngen-j contributors
License-Expression: MIT
Project-URL: Homepage, https://github.com/mamatnurahmat/ngen-japi
Project-URL: Repository, https://github.com/mamatnurahmat/ngen-japi
Project-URL: Issues, https://github.com/mamatnurahmat/ngen-japi/issues
Keywords: cli,wrapper,command,dispatch,jenkins,api
Classifier: Development Status :: 3 - Alpha
Classifier: Intended Audience :: Developers
Classifier: Programming Language :: Python :: 3
Classifier: Programming Language :: Python :: 3.7
Classifier: Programming Language :: Python :: 3.8
Classifier: Programming Language :: Python :: 3.9
Classifier: Programming Language :: Python :: 3.10
Classifier: Programming Language :: Python :: 3.11
Requires-Python: >=3.7
Requires-Dist: api4jenkins>=1.0.0
